delaunay_triangulation/__init__.py
delaunay_triangulation/triangulate.py
delaunay_triangulation/typing.py
delaunay_triangulation-1.0.4.dist-info/LICENSE
delaunay_triangulation-1.0.4.dist-info/METADATA
delaunay_triangulation-1.0.4.dist-info/WHEEL
delaunay_triangulation-1.0.4.dist-info/top_level.txt
delaunay_triangulation-1.0.4.dist-info/RECORD
