Metadata-Version: 2.1
Name: delaunay-triangulation
Version: 1.0.4
Summary: A lightweight collection of helper classes and methods to create a delaunay triangulation.
Home-page: UNKNOWN
Author: LeoniePiggy
Author-email: simon.henkel@gmx.de
License: UNKNOWN
Project-URL: Source Files, https://gitlab.com/LeoniePiggy/delaunay-triangulation-py
Platform: UNKNOWN
Classifier: Programming Language :: Python :: 3
Classifier: License :: OSI Approved :: MIT License
Classifier: Operating System :: OS Independent
Requires-Python: >=3.6
License-File: LICENSE
